<?xml version="1.0" encoding="UTF-8"?>
<con:soapui-project id="a35f7854-5b7f-453e-a291-e56e0e29999d" created="3.62.0" activeEnvironment="Default environment" encryptionMode="Not encrypted" name="REST Project 1" projectVersion="" updated="3.62.0 2025-09-03T10:21:09Z" resourceRoot="" xmlns:con="http://eviware.com/soapui/config">
  <con:settings/>
  <con:interface xsi:type="con:RestService" id="8d5092c3-0395-4a6d-a299-fbf79ef86ad8" wadlVersion="http://wadl.dev.java.net/2009/02" name="https://petstore.swagger.io" type="rest" xmlns:xsi="http://www.w3.org/2001/XMLSchema-instance">
    <con:settings id="635ba5db-41a8-412a-8812-af95382542bf"/>
    <con:definitionCache type="TEXT" rootPart=""/>
    <con:endpoints>
      <con:endpoint>https://petstore.swagger.io</con:endpoint>
    </con:endpoints>
    <con:resource name="User" path="/v2/user" id="7d350a29-db9a-48c7-b871-f74a139ed7ce">
      <con:settings/>
      <con:parameters/>
      <con:method name="User" id="cf6e02dc-f684-4797-8b8b-38023ccca0b8" method="POST">
        <con:settings/>
        <con:parameters/>
        <con:representation type="REQUEST">
          <con:mediaType>application/json</con:mediaType>
          <con:params/>
        </con:representation>
        <con:representation type="RESPONSE">
          <con:mediaType>application/json</con:mediaType>
          <con:status>200</con:status>
          <con:params/>
          <con:element xmlns:user="https://petstore.swagger.io/v2/user">user:Response</con:element>
        </con:representation>
        <con:request name="Request 1" id="bdc7ae37-c101-4519-9869-3fca4014205d" mediaType="application/json" postQueryString="false">
          <con:settings/>
          <con:endpoint>https://petstore.swagger.io</con:endpoint>
          <con:request/>
          <con:credentials>
            <con:selectedAuthProfile>No Authorization</con:selectedAuthProfile>
            <con:authType>No Authorization</con:authType>
          </con:credentials>
          <con:jmsConfig JMSDeliveryMode="PERSISTENT"/>
          <con:parameters/>
        </con:request>
      </con:method>
    </con:resource>
    <con:resource name="Login" path="/v2/user/login" id="903d4772-4e36-4506-b448-aaf527a0f61e">
      <con:settings/>
      <con:parameters/>
      <con:method name="Login" id="07ad2a0c-7a9f-4d44-9fab-3512d59dbb87" method="GET">
        <con:settings/>
        <con:parameters>
          <con:parameter required="true">
            <con:name>username</con:name>
            <con:value>{username}</con:value>
            <con:style>QUERY</con:style>
            <con:default>{username}</con:default>
            <con:path xsi:nil="true"/>
            <con:description xsi:nil="true"/>
          </con:parameter>
          <con:parameter required="true">
            <con:name>password</con:name>
            <con:value>{password}</con:value>
            <con:style>QUERY</con:style>
            <con:default>{password}</con:default>
            <con:path xsi:nil="true"/>
            <con:description xsi:nil="true"/>
          </con:parameter>
        </con:parameters>
        <con:representation type="RESPONSE">
          <con:mediaType>application/json</con:mediaType>
          <con:status>200</con:status>
          <con:params/>
          <con:element xmlns:log="https://petstore.swagger.io/v2/user/login">log:Response</con:element>
        </con:representation>
        <con:request name="Request 1" id="6690001a-e1a2-4cc9-8c92-854a1197c388" mediaType="application/json">
          <con:settings/>
          <con:endpoint>https://petstore.swagger.io</con:endpoint>
          <con:request/>
          <con:credentials>
            <con:selectedAuthProfile>No Authorization</con:selectedAuthProfile>
            <con:authType>No Authorization</con:authType>
          </con:credentials>
          <con:jmsConfig JMSDeliveryMode="PERSISTENT"/>
          <con:parameters>
            <con:entry key="password" value="{password}"/>
            <con:entry key="username" value="{username}"/>
          </con:parameters>
          <con:parameterOrder>
            <con:entry>username</con:entry>
            <con:entry>password</con:entry>
          </con:parameterOrder>
        </con:request>
      </con:method>
    </con:resource>
    <con:resource name="Username" path="/v2/user/{username}" id="82eb94b2-392c-4d17-b1a2-e768c11150fc">
      <con:settings/>
      <con:parameters/>
      <con:method name="Username" id="8375f1a7-fe3f-41ca-935c-0794f61e522e" method="GET">
        <con:settings/>
        <con:parameters>
          <con:parameter required="true">
            <con:name>username</con:name>
            <con:value>username</con:value>
            <con:style>TEMPLATE</con:style>
            <con:default>username</con:default>
            <con:path xsi:nil="true"/>
            <con:description xsi:nil="true"/>
          </con:parameter>
        </con:parameters>
        <con:representation type="FAULT">
          <con:mediaType>application/json</con:mediaType>
          <con:status>404</con:status>
          <con:params/>
          <con:element xmlns:user="https://petstore.swagger.io/v2/user/username">user:Fault</con:element>
        </con:representation>
        <con:representation type="RESPONSE">
          <con:mediaType>application/json</con:mediaType>
          <con:status>200</con:status>
          <con:params/>
          <con:element xmlns:user="https://petstore.swagger.io/v2/user/username">user:Response</con:element>
        </con:representation>
        <con:request name="Request 1" id="d18518cf-9d30-45ff-b958-18c03cbc44e7" mediaType="application/json">
          <con:settings/>
          <con:endpoint>https://petstore.swagger.io</con:endpoint>
          <con:credentials>
            <con:selectedAuthProfile>No Authorization</con:selectedAuthProfile>
            <con:authType>No Authorization</con:authType>
          </con:credentials>
          <con:parameters>
            <con:entry key="username" value="username"/>
          </con:parameters>
          <con:parameterOrder>
            <con:entry>username</con:entry>
          </con:parameterOrder>
        </con:request>
      </con:method>
      <con:method name="Username 2" id="baa78cd1-0c3f-4967-a555-18148cb28531" method="DELETE">
        <con:settings/>
        <con:parameters>
          <con:parameter required="true">
            <con:name>username</con:name>
            <con:value>username</con:value>
            <con:style>TEMPLATE</con:style>
            <con:default>username</con:default>
            <con:path xsi:nil="true"/>
            <con:description xsi:nil="true"/>
          </con:parameter>
        </con:parameters>
        <con:representation type="REQUEST">
          <con:mediaType>application/json</con:mediaType>
          <con:params/>
        </con:representation>
        <con:representation type="RESPONSE">
          <con:mediaType>application/json</con:mediaType>
          <con:status>200</con:status>
          <con:params/>
          <con:element xmlns:tes="https://petstore.swagger.io/v2/user/testuser">tes:Response</con:element>
        </con:representation>
        <con:representation type="FAULT">
          <con:mediaType xsi:nil="true"/>
          <con:status>404</con:status>
          <con:params/>
          <con:element>data</con:element>
        </con:representation>
        <con:request name="Request 1" id="4e0a165e-2985-4346-9fb3-ee4421d7b53b" mediaType="application/json">
          <con:settings/>
          <con:endpoint>https://petstore.swagger.io</con:endpoint>
          <con:credentials>
            <con:selectedAuthProfile>No Authorization</con:selectedAuthProfile>
            <con:authType>No Authorization</con:authType>
          </con:credentials>
          <con:parameters>
            <con:entry key="username" value="username"/>
          </con:parameters>
          <con:parameterOrder>
            <con:entry>username</con:entry>
          </con:parameterOrder>
        </con:request>
      </con:method>
    </con:resource>
    <con:resource name="Logout" path="/v2/user/logout" id="2c20d64d-38d0-42bd-a131-ba8899cc89a2">
      <con:settings/>
      <con:parameters/>
      <con:method name="Logout" id="08dde0e1-2ab9-4c01-b0ae-5994b9a742c7" method="GET">
        <con:settings/>
        <con:parameters>
          <con:parameter required="true">
            <con:name>username</con:name>
            <con:value/>
            <con:style>TEMPLATE</con:style>
            <con:default/>
          </con:parameter>
        </con:parameters>
        <con:representation type="RESPONSE">
          <con:mediaType>application/json</con:mediaType>
          <con:status>200</con:status>
          <con:params/>
          <con:element xmlns:log="https://petstore.swagger.io/v2/user/logout">log:Response</con:element>
        </con:representation>
        <con:request name="Request 1" id="716a4a15-8e41-4908-92dc-af4d8135b497" mediaType="application/json">
          <con:settings/>
          <con:endpoint>https://petstore.swagger.io</con:endpoint>
          <con:request/>
          <con:credentials>
            <con:selectedAuthProfile>No Authorization</con:selectedAuthProfile>
            <con:authType>No Authorization</con:authType>
          </con:credentials>
          <con:jmsConfig JMSDeliveryMode="PERSISTENT"/>
          <con:parameters>
            <con:entry key="username" value="0"/>
          </con:parameters>
          <con:parameterOrder>
            <con:entry>username</con:entry>
          </con:parameterOrder>
        </con:request>
      </con:method>
    </con:resource>
  </con:interface>
  <con:interface xsi:type="con:RestService" id="5e221161-45fb-47de-886f-ece80d001aa6" wadlVersion="http://wadl.dev.java.net/2009/02" name="http://ipwhois.app" type="rest" xmlns:xsi="http://www.w3.org/2001/XMLSchema-instance">
    <con:settings id="7bae419a-0440-4205-81f1-8e9e9bf004f3"/>
    <con:definitionCache type="TEXT" rootPart=""/>
    <con:endpoints>
      <con:endpoint>http://ipwhois.app</con:endpoint>
    </con:endpoints>
    <con:resource name="IP" path="/json/{IP}" id="a87adb9d-573f-4c48-9247-72f999e92f3c">
      <con:settings/>
      <con:parameters/>
      <con:method name="IP" id="f4dfb0d7-ee1d-4c20-b9c4-38728f7f78e3" method="GET">
        <con:settings/>
        <con:parameters>
          <con:parameter required="true">
            <con:name>IP</con:name>
            <con:value>IP</con:value>
            <con:style>TEMPLATE</con:style>
            <con:default>IP</con:default>
            <con:path xsi:nil="true"/>
            <con:description xsi:nil="true"/>
          </con:parameter>
        </con:parameters>
        <con:representation type="RESPONSE">
          <con:mediaType>application/json; charset=utf-8</con:mediaType>
          <con:status>200</con:status>
          <con:params/>
          <con:element xmlns:ns="http://ipwhois.app/json/66.12.25.226">ns:Response</con:element>
        </con:representation>
        <con:request name="Request 1" id="7e7660a3-0096-490b-8844-49bacd42a424" mediaType="application/json">
          <con:settings/>
          <con:endpoint>http://ipwhois.app</con:endpoint>
          <con:parameters>
            <con:entry key="IP" value="IP"/>
          </con:parameters>
          <con:parameterOrder>
            <con:entry>IP</con:entry>
          </con:parameterOrder>
        </con:request>
      </con:method>
    </con:resource>
  </con:interface>
  <con:testSuite id="c967d773-f034-4db6-a9d3-73cbf0b87fa0" name="https://petstore.swagger.io Test Suite">
    <con:settings id="185cf6c1-28ce-46d2-a4e9-ad20d026f555"/>
    <con:runType>SEQUENTIAL</con:runType>
    <con:testCase id="1a74535e-ce91-42df-a87e-af54fc0e8349" discardOkResults="false" failOnError="false" failTestCaseOnErrors="true" keepSession="false" name="Test Case" searchProperties="true" timeout="0">
      <con:settings/>
      <con:testStep type="restrequest" name="POST" id="3ceef7ba-ccdf-49c0-ad41-185372081cf9">
        <con:settings/>
        <con:config service="https://petstore.swagger.io" resourcePath="/v2/user" methodName="User" xsi:type="con:RestRequestStep" xmlns:xsi="http://www.w3.org/2001/XMLSchema-instance">
          <con:restRequest name="POST" id="bdc7ae37-c101-4519-9869-3fca4014205d" mediaType="application/json" postQueryString="false">
            <con:settings>
              <con:setting id="com.eviware.soapui.impl.wsdl.WsdlRequest@request-headers">&lt;xml-fragment/></con:setting>
            </con:settings>
            <con:endpoint>https://petstore.swagger.io</con:endpoint>
            <con:request>{
    "id": 1,
    "username": "testuser1",
    "firstName": "John",
    "lastName": "Doe",
    "email": "john@doe.com",
    "password": "testuser1",
    "phone": "234567422",
    "userStatus": 0
}</con:request>
            <con:originalUri>https://petstore.swagger.io/v2/user</con:originalUri>
            <con:assertion type="Valid HTTP Status Codes" id="cff6d2dc-1266-4c66-ad91-1725e2d92bb3" name="Valid HTTP Status Codes">
              <con:settings/>
              <con:configuration>
                <codes>200</codes>
              </con:configuration>
            </con:assertion>
            <con:credentials>
              <con:selectedAuthProfile>No Authorization</con:selectedAuthProfile>
              <con:authType>No Authorization</con:authType>
            </con:credentials>
            <con:jmsConfig JMSDeliveryMode="PERSISTENT"/>
            <con:parameters/>
          </con:restRequest>
        </con:config>
      </con:testStep>
      <con:testStep type="transfer" name="Property Transfer" id="7cda1b76-56e2-49a8-9cb5-22b33a893b7a">
        <con:settings/>
        <con:config xsi:type="con:PropertyTransfersStep" xmlns:xsi="http://www.w3.org/2001/XMLSchema-instance">
          <con:transfers setNullOnMissingSource="true" transferTextContent="true" failOnError="true" ignoreEmpty="false" transferToAll="false" entitize="false" transferChildNodes="false">
            <con:name>LoginTransferUsername</con:name>
            <con:sourceType>Request</con:sourceType>
            <con:sourceStep>POST</con:sourceStep>
            <con:sourcePath>$['username']</con:sourcePath>
            <con:targetType>username</con:targetType>
            <con:targetStep>LOGIN</con:targetStep>
            <con:targetPath/>
            <con:type>JSONPATH</con:type>
            <con:targetTransferType>JSONPATH</con:targetTransferType>
            <con:upgraded>true</con:upgraded>
          </con:transfers>
          <con:transfers setNullOnMissingSource="true" transferTextContent="true" failOnError="true" ignoreEmpty="false" transferToAll="false" entitize="false" transferChildNodes="false">
            <con:name>LoginTransferPassword</con:name>
            <con:sourceType>Request</con:sourceType>
            <con:sourceStep>POST</con:sourceStep>
            <con:sourcePath>$['password']</con:sourcePath>
            <con:targetType>password</con:targetType>
            <con:targetStep>LOGIN</con:targetStep>
            <con:type>JSONPATH</con:type>
            <con:targetTransferType>JSONPATH</con:targetTransferType>
            <con:upgraded>true</con:upgraded>
          </con:transfers>
          <con:transfers setNullOnMissingSource="true" transferTextContent="true" failOnError="true" ignoreEmpty="false" transferToAll="false" entitize="false" transferChildNodes="false">
            <con:name>GetTransferUsername</con:name>
            <con:sourceType>Request</con:sourceType>
            <con:sourceStep>POST</con:sourceStep>
            <con:sourcePath>$['username']</con:sourcePath>
            <con:targetType>username</con:targetType>
            <con:targetStep>GET</con:targetStep>
            <con:type>JSONPATH</con:type>
            <con:upgraded>true</con:upgraded>
          </con:transfers>
        </con:config>
      </con:testStep>
      <con:testStep type="restrequest" name="LOGIN" id="748ac992-37cc-46f6-9bde-16d09ca0ec57">
        <con:settings/>
        <con:config service="https://petstore.swagger.io" resourcePath="/v2/user/login" methodName="Login" xsi:type="con:RestRequestStep" xmlns:xsi="http://www.w3.org/2001/XMLSchema-instance">
          <con:restRequest name="LOGIN" id="6690001a-e1a2-4cc9-8c92-854a1197c388" mediaType="application/json">
            <con:settings>
              <con:setting id="com.eviware.soapui.impl.wsdl.WsdlRequest@request-headers">&lt;xml-fragment/></con:setting>
            </con:settings>
            <con:endpoint>https://petstore.swagger.io</con:endpoint>
            <con:request/>
            <con:originalUri>https://petstore.swagger.io/v2/user/login</con:originalUri>
            <con:assertion type="Valid HTTP Status Codes" id="2f129c79-2cb0-48ae-a47b-f6c888950b17" name="Valid HTTP Status Codes">
              <con:settings/>
              <con:configuration>
                <codes>200</codes>
              </con:configuration>
            </con:assertion>
            <con:credentials>
              <con:username>testuser1</con:username>
              <con:selectedAuthProfile>No Authorization</con:selectedAuthProfile>
              <con:authType>No Authorization</con:authType>
            </con:credentials>
            <con:jmsConfig JMSDeliveryMode="PERSISTENT"/>
            <con:parameters>
              <con:entry key="password" value="testuser1"/>
              <con:entry key="username" value="testuser1"/>
            </con:parameters>
            <con:parameterOrder>
              <con:entry>username</con:entry>
              <con:entry>password</con:entry>
            </con:parameterOrder>
          </con:restRequest>
        </con:config>
      </con:testStep>
      <con:testStep type="restrequest" name="GET" id="4e1ff91d-5a3a-495a-b416-6ce03789b594">
        <con:settings/>
        <con:config service="https://petstore.swagger.io" resourcePath="/v2/user/{username}" methodName="Username" xsi:type="con:RestRequestStep" xmlns:xsi="http://www.w3.org/2001/XMLSchema-instance">
          <con:restRequest name="GET" id="d18518cf-9d30-45ff-b958-18c03cbc44e7" mediaType="application/json">
            <con:settings>
              <con:setting id="com.eviware.soapui.impl.wsdl.WsdlRequest@request-headers">&lt;xml-fragment/></con:setting>
            </con:settings>
            <con:endpoint>https://petstore.swagger.io</con:endpoint>
            <con:request/>
            <con:originalUri>https://petstore.swagger.io/v2/user/username</con:originalUri>
            <con:assertion type="Valid HTTP Status Codes" id="8802625b-197d-44ba-93de-e9ddf454b818" name="Valid HTTP Status Codes">
              <con:settings/>
              <con:configuration>
                <codes>200</codes>
              </con:configuration>
            </con:assertion>
            <con:assertion type="JsonPath Match" id="05fd3134-4ee4-4b03-a51b-cd9fb0c84bdb" name="JSONPath Match">
              <con:configuration>
                <path>$['username']</path>
                <content>testuser</content>
                <allowWildcards>false</allowWildcards>
                <ignoreNamspaceDifferences>false</ignoreNamspaceDifferences>
                <ignoreComments>false</ignoreComments>
              </con:configuration>
            </con:assertion>
            <con:credentials>
              <con:selectedAuthProfile>No Authorization</con:selectedAuthProfile>
              <con:authType>No Authorization</con:authType>
            </con:credentials>
            <con:jmsConfig JMSDeliveryMode="PERSISTENT"/>
            <con:parameters>
              <con:entry key="username" value="testuser1"/>
            </con:parameters>
            <con:parameterOrder>
              <con:entry>username</con:entry>
            </con:parameterOrder>
          </con:restRequest>
        </con:config>
      </con:testStep>
      <con:testStep type="restrequest" name="LOGOUT" id="b99774ea-48a9-477f-84c7-e7790656aa07">
        <con:settings/>
        <con:config service="https://petstore.swagger.io" resourcePath="/v2/user/logout" methodName="Logout" xsi:type="con:RestRequestStep" xmlns:xsi="http://www.w3.org/2001/XMLSchema-instance">
          <con:restRequest name="LOGOUT" id="716a4a15-8e41-4908-92dc-af4d8135b497" mediaType="application/json">
            <con:settings>
              <con:setting id="com.eviware.soapui.impl.wsdl.WsdlRequest@request-headers">&lt;xml-fragment/></con:setting>
            </con:settings>
            <con:endpoint>https://petstore.swagger.io</con:endpoint>
            <con:request/>
            <con:originalUri>https://petstore.swagger.io/v2/user/logout</con:originalUri>
            <con:assertion type="Valid HTTP Status Codes" id="9b065412-8eb9-422d-886e-e7738fc6a91e" name="Valid HTTP Status Codes">
              <con:settings/>
              <con:configuration>
                <codes>200</codes>
              </con:configuration>
            </con:assertion>
            <con:credentials>
              <con:selectedAuthProfile>No Authorization</con:selectedAuthProfile>
              <con:authType>No Authorization</con:authType>
            </con:credentials>
            <con:jmsConfig JMSDeliveryMode="PERSISTENT"/>
            <con:parameters>
              <con:entry key="username" value="testuser"/>
            </con:parameters>
            <con:parameterOrder>
              <con:entry>username</con:entry>
            </con:parameterOrder>
          </con:restRequest>
        </con:config>
      </con:testStep>
      <con:testStep type="restrequest" name="DELETE" id="54555971-b5db-4d53-ad4d-1f8e6733c9b2">
        <con:settings/>
        <con:config service="https://petstore.swagger.io" resourcePath="/v2/user/{username}" methodName="Username 2" xsi:type="con:RestRequestStep" xmlns:xsi="http://www.w3.org/2001/XMLSchema-instance">
          <con:restRequest name="DELETE" id="4e0a165e-2985-4346-9fb3-ee4421d7b53b" mediaType="application/json" postQueryString="false">
            <con:settings>
              <con:setting id="com.eviware.soapui.impl.wsdl.WsdlRequest@request-headers">&lt;xml-fragment/></con:setting>
            </con:settings>
            <con:endpoint>https://petstore.swagger.io</con:endpoint>
            <con:request/>
            <con:originalUri>https://petstore.swagger.io/v2/user/testuser</con:originalUri>
            <con:assertion type="Valid HTTP Status Codes" id="9c458765-8843-4075-a5c7-3e8ee4dc3a8c" name="Valid HTTP Status Codes">
              <con:settings/>
              <con:configuration>
                <codes>200</codes>
              </con:configuration>
            </con:assertion>
            <con:credentials>
              <con:selectedAuthProfile>No Authorization</con:selectedAuthProfile>
              <con:authType>No Authorization</con:authType>
            </con:credentials>
            <con:jmsConfig JMSDeliveryMode="PERSISTENT"/>
            <con:parameters>
              <con:entry key="username" value="testuser"/>
            </con:parameters>
            <con:parameterOrder>
              <con:entry>username</con:entry>
            </con:parameterOrder>
          </con:restRequest>
        </con:config>
      </con:testStep>
      <con:properties/>
      <con:reportParameters/>
    </con:testCase>
    <con:properties/>
    <con:reportParameters/>
  </con:testSuite>
  <con:testSuite id="d5b81fd2-55d3-4bb9-ab43-8014d90224c4" name="http://ipwhois.app Test Suite">
    <con:settings id="d0207cc6-2729-45fe-ada8-c587cf5dd1d6"/>
    <con:runType>SEQUENTIAL</con:runType>
    <con:testCase id="af3ed05b-9a57-480b-bfad-2177deafde07" discardOkResults="false" failOnError="false" failTestCaseOnErrors="true" keepSession="false" name="http://ipwhois.app Test Case 1" searchProperties="true" timeout="0">
      <con:settings/>
      <con:testStep type="datasource" name="DataSource" id="af727b49-a6db-44c3-a7b5-02446a027d34">
        <con:settings/>
        <con:config xsi:type="con:DataSourceStep" xmlns:xsi="http://www.w3.org/2001/XMLSchema-instance">
          <con:dataSource type="File">
            <con:configuration>
              <fileName>C:/Users/004PM1744/OneDrive - IBM/My docs_One drive/Srikanth/Learning/MM/API Testing/sample data.txt</fileName>
              <separator>,</separator>
              <trim>true</trim>
              <charset>Cp1252</charset>
              <quotedValues>false</quotedValues>
            </con:configuration>
          </con:dataSource>
          <con:shared>true</con:shared>
          <con:restartShared>true</con:restartShared>
          <con:property>address</con:property>
          <con:restartOnRun>true</con:restartOnRun>
          <con:stopDatasourceExhausted>false</con:stopDatasourceExhausted>
        </con:config>
      </con:testStep>
      <con:testStep type="restrequest" name="Request 1" id="adb74477-3fa5-480c-a534-b42bf0a63e7d">
        <con:settings/>
        <con:config service="http://ipwhois.app" resourcePath="/json/{IP}" methodName="IP" xsi:type="con:RestRequestStep" xmlns:xsi="http://www.w3.org/2001/XMLSchema-instance">
          <con:restRequest name="Request 1" id="7e7660a3-0096-490b-8844-49bacd42a424" mediaType="application/json">
            <con:settings>
              <con:setting id="com.eviware.soapui.impl.wsdl.WsdlRequest@request-headers">&lt;xml-fragment/></con:setting>
            </con:settings>
            <con:endpoint>http://ipwhois.app</con:endpoint>
            <con:request/>
            <con:originalUri>http://ipwhois.app/json/66.12.25.226</con:originalUri>
            <con:assertion type="Valid HTTP Status Codes" id="b412ee05-13c8-4d6f-9436-60798a07b218" name="Valid HTTP Status Codes">
              <con:settings/>
              <con:configuration>
                <codes>200</codes>
              </con:configuration>
            </con:assertion>
            <con:assertion type="JsonPath Match" id="8b220cd6-d917-4a3c-9fc8-6234bdb98118" name="JSONPath Match">
              <con:configuration>
                <path>$['country']</path>
                <content>"United States"</content>
                <allowWildcards>false</allowWildcards>
                <ignoreNamspaceDifferences>false</ignoreNamspaceDifferences>
                <ignoreComments>false</ignoreComments>
              </con:configuration>
            </con:assertion>
            <con:credentials>
              <con:selectedAuthProfile>No Authorization</con:selectedAuthProfile>
              <con:authType>No Authorization</con:authType>
            </con:credentials>
            <con:jmsConfig JMSDeliveryMode="PERSISTENT"/>
            <con:parameters>
              <con:entry key="IP" value="${DataSource#address}"/>
            </con:parameters>
            <con:parameterOrder>
              <con:entry>IP</con:entry>
            </con:parameterOrder>
          </con:restRequest>
        </con:config>
      </con:testStep>
      <con:testStep type="datasourceloop" name="Data Source Loop" id="aeee8536-a350-4297-b8e2-f0d1168c500d">
        <con:settings/>
        <con:config>
          <dataSourceStep>DataSource</dataSourceStep>
          <targetStep>Request 1</targetStep>
          <discardResults>true</discardResults>
        </con:config>
      </con:testStep>
      <con:properties/>
      <con:reportParameters/>
    </con:testCase>
    <con:properties/>
    <con:reportParameters/>
  </con:testSuite>
  <con:requirements/>
  <con:properties/>
  <con:wssContainer/>
  <con:databaseConnectionContainer/>
  <con:jmsConnectionContainer/>
  <con:oAuth2ProfileContainer/>
  <con:oAuth1ProfileContainer/>
  <con:reporting>
    <con:xmlTemplates/>
    <con:parameters/>
  </con:reporting>
  <con:eventHandlers type="RequestFilter.filterRequest" name="RequestFilter.filterRequest">
    <con:script>// Sample event script to add custom HTTP header to all outgoing REST, SOAP and HTTP(S) calls
// This code is often used for adding custom authentication to ReadyAPI functional tests

// If hardcoding the token, uncomment and change line 5
// token = '4567'

// If your token is parameterized in Project level custom property, uncomment line 8
// token = request.parent.testCase.testSuite.project.getProperty('auth_token').getValue()

// To modify all outgoing calls, remove comments from lines 11 to 16
// headers = request.requestHeaders
// if (headers.containsKey('auth_token2') == false) {
//   headers.put('auth_token2', token)
//   request.requestHeaders = headers
// }</con:script>
  </con:eventHandlers>
  <con:eventHandlers type="TestRunListener.afterStep" name="TestRunListener.afterStep">
    <con:script>// Save all test step results into files
// Change the directory path in line 5 to a location where you want to store details
// then uncomment lines 5 to 10

// filePath = 'C:\\tempOutputDirectory\\'
// fos = new java.io.FileOutputStream(filePath + testStepResult.testStep.label + '.txt', true)
// pw = new java.io.PrintWriter(fos)
// testStepResult.writeTo(pw)
// pw.close()
// fos.close()</con:script>
  </con:eventHandlers>
  <con:authRepository/>
  <con:tags/>
</con:soapui-project>